chatterbox_onnx/__init__.py
chatterbox_onnx/opm.py
chatterbox_onnx/scripts.py
chatterbox_onnx/version.py
chatterbox_onnx-0.2.1.dist-info/METADATA
chatterbox_onnx-0.2.1.dist-info/WHEEL
chatterbox_onnx-0.2.1.dist-info/entry_points.txt
chatterbox_onnx-0.2.1.dist-info/top_level.txt
chatterbox_onnx-0.2.1.dist-info/RECORD
