Metadata-Version: 2.4
Name: chatterbox_onnx
Version: 0.2.1
Home-page: https://github.com/TigreGotico/chatterbox_onnx
Author: JarbasAi
Author-email: jarbasai@mailfence.com
License: MIT
Requires-Dist: librosa
Requires-Dist: numpy
Requires-Dist: onnxruntime
Requires-Dist: soundfile
Requires-Dist: huggingface_hub
Requires-Dist: click
Requires-Dist: tokenizers
Dynamic: author
Dynamic: author-email
Dynamic: home-page
Dynamic: license
Dynamic: requires-dist
